{
  "$schema": "http://adaptivecards.io/schemas/adaptive-card.json",
  "type": "AdaptiveCard",
  "version": "1.0",
  "body": [
    {
      "type": "Image",
      "url": "https://img.freepik.com/premium-vector/robot-pictogram-bot-tekenontwerp-chatbot-symbool-concept-voice-supportservice-bot-online-support-bot-vector-stock-illustratie_100456-34.jpg?w=740",
      "size": "stretch"
    },
    {
      "type": "TextBlock",
      "spacing": "medium",
      "size": "default",
      "weight": "bolder",
      "text": "Welcome to Fly Me ! I am Patrick I will assist you today !",
      "wrap": true,
      "maxLines": 0
    },
    {
      "type": "TextBlock",
      "size": "default",
      "isSubtle": "true",
      "text": "At any time during our conversation you can type HELP to get advice or CANCEL to go back to the initial menu",
      "wrap": true,
      "maxLines": 0
    }
  ]
  
}